{"files":{"packages/shared/dist/ai-schemas.d.ts":{"size":1885,"mtime_nanos":1775702135329182938,"mode":420,"is_dir":false},"packages/shared/dist/ai-schemas.d.ts.map":{"size":546,"mtime_nanos":1775702135329063816,"mode":420,"is_dir":false},"packages/shared/dist/index.js":{"size":936,"mtime_nanos":1775702135341430942,"mode":420,"is_dir":false},"packages/shared/dist/enums.js":{"size":3937,"mtime_nanos":1775702135314849739,"mode":420,"is_dir":false},"packages/shared/dist/schemas.js":{"size":3808,"mtime_nanos":1775702135336417827,"mode":420,"is_dir":false},"packages/shared/.turbo/turbo-build.log":{"size":81,"mtime_nanos":1775702135356161130,"mode":420,"is_dir":false},"packages/shared/dist/index.d.ts":{"size":142,"mtime_nanos":1775702135341877597,"mode":420,"is_dir":false},"packages/shared/dist/index.d.ts.map":{"size":186,"mtime_nanos":1775702135341785433,"mode":420,"is_dir":false},"packages/shared/dist/enums.d.ts.map":{"size":1136,"mtime_nanos":1775702135319448574,"mode":420,"is_dir":false},"packages/shared/dist/schemas.d.ts":{"size":2944,"mtime_nanos":1775702135340500884,"mode":420,"is_dir":false},"packages/shared/dist/types.d.ts":{"size":4378,"mtime_nanos":1775702135333082583,"mode":420,"is_dir":false},"packages/shared/dist/types.d.ts.map":{"size":4673,"mtime_nanos":1775702135332664136,"mode":420,"is_dir":false},"packages/shared/dist/schemas.d.ts.map":{"size":551,"mtime_nanos":1775702135340360305,"mode":420,"is_dir":false},"packages/shared/dist":{"size":0,"mtime_nanos":0,"mode":0,"is_dir":true},"packages/shared/dist/types.js":{"size":77,"mtime_nanos":1775702135329554970,"mode":420,"is_dir":false},"packages/shared/dist/enums.d.ts":{"size":1815,"mtime_nanos":1775702135319574863,"mode":420,"is_dir":false},"packages/shared/dist/ai-schemas.js":{"size":1524,"mtime_nanos":1775702135321959507,"mode":420,"is_dir":false}},"order":["packages/shared/.turbo/turbo-build.log","packages/shared/dist","packages/shared/dist/ai-schemas.d.ts","packages/shared/dist/ai-schemas.d.ts.map","packages/shared/dist/ai-schemas.js","packages/shared/dist/enums.d.ts","packages/shared/dist/enums.d.ts.map","packages/shared/dist/enums.js","packages/shared/dist/index.d.ts","packages/shared/dist/index.d.ts.map","packages/shared/dist/index.js","packages/shared/dist/schemas.d.ts","packages/shared/dist/schemas.d.ts.map","packages/shared/dist/schemas.js","packages/shared/dist/types.d.ts","packages/shared/dist/types.d.ts.map","packages/shared/dist/types.js"]}